{
    "model": {
        "type": "range_dispatch",
        "property": "custom_model_data",
        "fallback": {
            "type": "minecraft:condition",
            "property": "minecraft:using_item",
            "on_false": {
                "type": "minecraft:model",
                "model": "minecraft:item/bow"
            },
            "on_true": {
                "type": "minecraft:range_dispatch",
                "property": "minecraft:use_duration",
                "scale": 0.05,
                "fallback": {
                    "type": "minecraft:model",
                    "model": "minecraft:item/bow_pulling_0"
                },
                "entries": [
                    {
                        "threshold": 0.65,
                        "model": {
                            "type": "minecraft:model",
                            "model": "minecraft:item/bow_pulling_1"
                        }
                    },
                    {
                        "threshold": 0.9,
                        "model": {
                            "type": "minecraft:model",
                            "model": "minecraft:item/bow_pulling_2"
                        }
                    }
                ]
            }
        },
        "entries": [
            {
                "threshold": 50001,
                "model": {
                    "type": "minecraft:condition",
                    "property": "minecraft:using_item",
                    "on_false": {
                        "type": "minecraft:model",
                        "model": "edoween:item/infernal_set/infernal_bow"
                    },
                    "on_true": {
                        "type": "minecraft:range_dispatch",
                        "property": "minecraft:use_duration",
                        "scale": 0.05,
                        "fallback": {
                            "type": "minecraft:model",
                            "model": "edoween:item/infernal_set/infernal_bow"
                        },
                        "entries": [
                            {
                                "threshold": 0.0,
                                "model": {
                                    "type": "minecraft:model",
                                    "model": "edoween:item/infernal_set/infernal_bow_pulling_0"
                                }
                            },
                            {
                                "threshold": 0.65,
                                "model": {
                                    "type": "minecraft:model",
                                    "model": "edoween:item/infernal_set/infernal_bow_pulling_1"
                                }
                            },
                            {
                                "threshold": 0.9,
                                "model": {
                                    "type": "minecraft:model",
                                    "model": "edoween:item/infernal_set/infernal_bow_pulling_2"
                                }
                            }
                        ]
                    }
                }
            },
            {
                "threshold": 50002,
                "model": {
                    "type": "minecraft:condition",
                    "property": "minecraft:using_item",
                    "on_false": {
                        "type": "minecraft:model",
                        "model": "edoween:item/bone_set/bone_bow"
                    },
                    "on_true": {
                        "type": "minecraft:range_dispatch",
                        "property": "minecraft:use_duration",
                        "scale": 0.05,
                        "fallback": {
                            "type": "minecraft:model",
                            "model": "edoween:item/bone_set/bone_bow"
                        },
                        "entries": [
                            {
                                "threshold": 0.0,
                                "model": {
                                    "type": "minecraft:model",
                                    "model": "edoween:item/bone_set/bone_bow_pulling_0"
                                }
                            },
                            {
                                "threshold": 0.65,
                                "model": {
                                    "type": "minecraft:model",
                                    "model": "edoween:item/bone_set/bone_bow_pulling_1"
                                }
                            },
                            {
                                "threshold": 0.9,
                                "model": {
                                    "type": "minecraft:model",
                                    "model": "edoween:item/bone_set/bone_bow_pulling_2"
                                }
                            }
                        ]
                    }
                }
            },
            {
                "threshold": 50003,
                "model": {
                    "type": "minecraft:condition",
                    "property": "minecraft:using_item",
                    "on_false": {
                        "type": "minecraft:model",
                        "model": "edoxmas:item/candy_cane_set/candy_cane_bow"
                    },
                    "on_true": {
                        "type": "minecraft:range_dispatch",
                        "property": "minecraft:use_duration",
                        "scale": 0.05,
                        "fallback": {
                            "type": "minecraft:model",
                            "model": "edoxmas:item/candy_cane_set/candy_cane_bow"
                        },
                        "entries": [
                            {
                                "threshold": 0.0,
                                "model": {
                                    "type": "minecraft:model",
                                    "model": "edoxmas:item/candy_cane_set/candy_cane_bow_pulling_0"
                                }
                            },
                            {
                                "threshold": 0.65,
                                "model": {
                                    "type": "minecraft:model",
                                    "model": "edoxmas:item/candy_cane_set/candy_cane_bow_pulling_1"
                                }
                            },
                            {
                                "threshold": 0.9,
                                "model": {
                                    "type": "minecraft:model",
                                    "model": "edoxmas:item/candy_cane_set/candy_cane_bow_pulling_2"
                                }
                            }
                        ]
                    }
                }
            },
            {
                "threshold": 50004,
                "model": {
                    "type": "minecraft:condition",
                    "property": "minecraft:using_item",
                    "on_false": {
                        "type": "minecraft:model",
                        "model": "edoxmas:item/glacial_set/glacial_bow"
                    },
                    "on_true": {
                        "type": "minecraft:range_dispatch",
                        "property": "minecraft:use_duration",
                        "scale": 0.05,
                        "fallback": {
                            "type": "minecraft:model",
                            "model": "edoxmas:item/glacial_set/glacial_bow"
                        },
                        "entries": [
                            {
                                "threshold": 0.0,
                                "model": {
                                    "type": "minecraft:model",
                                    "model": "edoxmas:item/glacial_set/glacial_bow_pulling_0"
                                }
                            },
                            {
                                "threshold": 0.65,
                                "model": {
                                    "type": "minecraft:model",
                                    "model": "edoxmas:item/glacial_set/glacial_bow_pulling_1"
                                }
                            },
                            {
                                "threshold": 0.9,
                                "model": {
                                    "type": "minecraft:model",
                                    "model": "edoxmas:item/glacial_set/glacial_bow_pulling_2"
                                }
                            }
                        ]
                    }
                }
            },
            {
                "threshold": 50005,
                "model": {
                    "type": "minecraft:condition",
                    "property": "minecraft:using_item",
                    "on_false": {
                        "type": "minecraft:model",
                        "model": "edovalentine:item/cupid_set/cupid_bow"
                    },
                    "on_true": {
                        "type": "minecraft:range_dispatch",
                        "property": "minecraft:use_duration",
                        "scale": 0.05,
                        "fallback": {
                            "type": "minecraft:model",
                            "model": "edovalentine:item/cupid_set/cupid_bow"
                        },
                        "entries": [
                            {
                                "threshold": 0.0,
                                "model": {
                                    "type": "minecraft:model",
                                    "model": "edovalentine:item/cupid_set/cupid_bow_pulling_0"
                                }
                            },
                            {
                                "threshold": 0.65,
                                "model": {
                                    "type": "minecraft:model",
                                    "model": "edovalentine:item/cupid_set/cupid_bow_pulling_1"
                                }
                            },
                            {
                                "threshold": 0.9,
                                "model": {
                                    "type": "minecraft:model",
                                    "model": "edovalentine:item/cupid_set/cupid_bow_pulling_2"
                                }
                            }
                        ]
                    }
                }
            },
            {
                "threshold": 50006,
                "model": {
                    "type": "minecraft:condition",
                    "property": "minecraft:using_item",
                    "on_false": {
                        "type": "minecraft:model",
                        "model": "edocarnival:item/carnival_set/carnival_bow"
                    },
                    "on_true": {
                        "type": "minecraft:range_dispatch",
                        "property": "minecraft:use_duration",
                        "scale": 0.05,
                        "fallback": {
                            "type": "minecraft:model",
                            "model": "edocarnival:item/carnival_set/carnival_bow"
                        },
                        "entries": [
                            {
                                "threshold": 0.0,
                                "model": {
                                    "type": "minecraft:model",
                                    "model": "edocarnival:item/carnival_set/carnival_bow_pulling_0"
                                }
                            },
                            {
                                "threshold": 0.65,
                                "model": {
                                    "type": "minecraft:model",
                                    "model": "edocarnival:item/carnival_set/carnival_bow_pulling_1"
                                }
                            },
                            {
                                "threshold": 0.9,
                                "model": {
                                    "type": "minecraft:model",
                                    "model": "edocarnival:item/carnival_set/carnival_bow_pulling_2"
                                }
                            }
                        ]
                    }
                }
            },
            {
                "threshold": 51000,
                "model": {
                    "type": "minecraft:condition",
                    "property": "minecraft:using_item",
                    "on_false": {
                        "type": "minecraft:model",
                        "model": "minecraft:item/bow"
                    },
                    "on_true": {
                        "type": "minecraft:range_dispatch",
                        "property": "minecraft:use_duration",
                        "scale": 0.05,
                        "fallback": {
                            "type": "minecraft:model",
                            "model": "minecraft:item/bow"
                        },
                        "entries": [
                            {
                                "threshold": 0.0,
                                "model": {
                                    "type": "minecraft:model",
                                    "model": "minecraft:item/bow_pulling_0"
                                }
                            },
                            {
                                "threshold": 0.65,
                                "model": {
                                    "type": "minecraft:model",
                                    "model": "minecraft:item/bow_pulling_1"
                                }
                            },
                            {
                                "threshold": 0.9,
                                "model": {
                                    "type": "minecraft:model",
                                    "model": "minecraft:item/bow_pulling_2"
                                }
                            }
                        ]
                    }
                }
            }
        ]
    }
}